{
  "id": "personal-research-workflow-blockers",
  "name": "personal-research-workflow-blockers",
  "title": "Fix personal research workflow blockers",
  "description": "Fix the verified personal workflow blockers without expanding product scope: global search, shortlist evidence handoff, in-context watchlist action, and trustworthy financial states.",
  "status": "in_progress",
  "dev_type": null,
  "scope": null,
  "package": null,
  "priority": "P1",
  "creator": "何剑锋",
  "assignee": "何剑锋",
  "createdAt": "2026-07-15",
  "completedAt": null,
  "branch": null,
  "base_branch": "master",
  "worktree_path": null,
  "commit": null,
  "pr_url": null,
  "subtasks": [],
  "children": [],
  "parent": "07-15-five-day-personal-research-acceptance",
  "relatedFiles": [],
  "notes": "",
  "meta": {}
}