{
  "id": "bootstrap-backend-guidelines",
  "name": "bootstrap-backend-guidelines",
  "title": "Bootstrap backend guidelines",
  "description": "",
  "status": "in_progress",
  "dev_type": null,
  "scope": null,
  "package": null,
  "priority": "P2",
  "creator": "何剑锋",
  "assignee": "何剑锋",
  "createdAt": "2026-07-02",
  "completedAt": null,
  "branch": null,
  "base_branch": "master",
  "worktree_path": null,
  "commit": null,
  "pr_url": null,
  "subtasks": [],
  "children": [],
  "parent": "07-02-parallel-remaining-backlog-execution",
  "relatedFiles": [],
  "notes": "",
  "meta": {}
}